[
  {
    "date": "2025-11-14",
    "category": "Data Science & Analytics",
    "job_count": 2,
    "rolling_7d": 2.0,
    "rolling_30d": 2.0
  },
  {
    "date": "2025-11-14",
    "category": "Software Engineering",
    "job_count": 1,
    "rolling_7d": 1.0,
    "rolling_30d": 1.0
  },
  {
    "date": "2025-11-19",
    "category": "Data Science & Analytics",
    "job_count": 1,
    "rolling_7d": 1.5,
    "rolling_30d": 1.5
  },
  {
    "date": "2025-11-25",
    "category": "Data Science & Analytics",
    "job_count": 1,
    "rolling_7d": 1.3333333333333333,
    "rolling_30d": 1.3333333333333333
  },
  {
    "date": "2025-12-01",
    "category": "Data Science & Analytics",
    "job_count": 2,
    "rolling_7d": 1.5,
    "rolling_30d": 1.5
  },
  {
    "date": "2025-12-02",
    "category": "Data Science & Analytics",
    "job_count": 2,
    "rolling_7d": 1.6,
    "rolling_30d": 1.6
  },
  {
    "date": "2025-12-05",
    "category": "Data Science & Analytics",
    "job_count": 3,
    "rolling_7d": 1.8333333333333333,
    "rolling_30d": 1.8333333333333333
  },
  {
    "date": "2025-12-05",
    "category": "DevOps & Infrastructure",
    "job_count": 2,
    "rolling_7d": 2.0,
    "rolling_30d": 2.0
  },
  {
    "date": "2025-12-05",
    "category": "Software Engineering",
    "job_count": 1,
    "rolling_7d": 1.0,
    "rolling_30d": 1.0
  },
  {
    "date": "2025-12-08",
    "category": "Data Science & Analytics",
    "job_count": 2,
    "rolling_7d": 1.8571428571428572,
    "rolling_30d": 1.8571428571428572
  },
  {
    "date": "2025-12-10",
    "category": "Data Science & Analytics",
    "job_count": 1,
    "rolling_7d": 1.7142857142857142,
    "rolling_30d": 1.75
  },
  {
    "date": "2025-12-10",
    "category": "Software Engineering",
    "job_count": 1,
    "rolling_7d": 1.0,
    "rolling_30d": 1.0
  }
]